jayrock/__init__.py
jayrock/instrument.py
jayrock/logging.py
jayrock/neatm.py
jayrock/observe.py
jayrock/plotting.py
jayrock/target.py
jayrock-0.0.3.dist-info/METADATA
jayrock-0.0.3.dist-info/WHEEL
jayrock-0.0.3.dist-info/RECORD
