Metadata-Version: 2.3
Name: jayrock
Version: 0.0.3
Summary: JWST observations planning for asteroids.
License: MIT
Author: Max Mahlke
Author-email: max.mahlke@rwth-aachen.de
Requires-Python: >=3.11
Classifier: License :: OSI Approved :: MIT License
Classifier: Programming Language :: Python :: 3
Classifier: Programming Language :: Python :: 3.11
Classifier: Programming Language :: Python :: 3.12
Classifier: Programming Language :: Python :: 3.13
Requires-Dist: astropy (>=7.1.1)
Requires-Dist: astroquery (>=0.4.11)
Requires-Dist: jwst-gtvt (>=1.1.1)
Requires-Dist: matplotlib (>=3.10.7)
Requires-Dist: numpy (>=2.3.4)
Requires-Dist: pandas (>=2.3.3)
Requires-Dist: pandeia-engine (>=2025.9)
Requires-Dist: rich (>=14.2.0)
Requires-Dist: scipy (>=1.16.2)
Requires-Dist: space-rocks (>=1.9.15)
Project-URL: Repository, https://github.com/maxmahlke/jayrock.git
